MANIFEST.in
README.md
setup.cfg
setup.py
Ultron_Rohon.egg-info/PKG-INFO
Ultron_Rohon.egg-info/SOURCES.txt
Ultron_Rohon.egg-info/dependency_links.txt
Ultron_Rohon.egg-info/not-zip-safe
Ultron_Rohon.egg-info/requires.txt
Ultron_Rohon.egg-info/top_level.txt
vnpy_rohon/__init__.py
vnpy_rohon/api/RohonBaseV64.dll
vnpy_rohon/api/WinDataCollect.dll
vnpy_rohon/api/__init__.py
vnpy_rohon/api/libLinuxDataCollect.so
vnpy_rohon/api/librohonbase.so
vnpy_rohon/api/libthostmduserapi_se.so
vnpy_rohon/api/libthosttraderapi_se.so
vnpy_rohon/api/rohon_constant.py
vnpy_rohon/api/thostmduserapi_se.dll
vnpy_rohon/api/thosttraderapi_se.dll
vnpy_rohon/api/vnrohonmd.cpython-36m-x86_64-linux-gnu.so
vnpy_rohon/api/vnrohontd.cpython-36m-x86_64-linux-gnu.so
vnpy_rohon/api/generator/rohon_md_header_define.h
vnpy_rohon/api/generator/rohon_md_header_function.h
vnpy_rohon/api/generator/rohon_md_header_on.h
vnpy_rohon/api/generator/rohon_md_header_process.h
vnpy_rohon/api/generator/rohon_md_source_function.cpp
vnpy_rohon/api/generator/rohon_md_source_module.cpp
vnpy_rohon/api/generator/rohon_md_source_on.cpp
vnpy_rohon/api/generator/rohon_md_source_process.cpp
vnpy_rohon/api/generator/rohon_md_source_switch.cpp
vnpy_rohon/api/generator/rohon_md_source_task.cpp
vnpy_rohon/api/generator/rohon_td_header_define.h
vnpy_rohon/api/generator/rohon_td_header_function.h
vnpy_rohon/api/generator/rohon_td_header_on.h
vnpy_rohon/api/generator/rohon_td_header_process.h
vnpy_rohon/api/generator/rohon_td_source_function.cpp
vnpy_rohon/api/generator/rohon_td_source_module.cpp
vnpy_rohon/api/generator/rohon_td_source_on.cpp
vnpy_rohon/api/generator/rohon_td_source_process.cpp
vnpy_rohon/api/generator/rohon_td_source_switch.cpp
vnpy_rohon/api/generator/rohon_td_source_task.cpp
vnpy_rohon/api/include/pybind11/attr.h
vnpy_rohon/api/include/pybind11/buffer_info.h
vnpy_rohon/api/include/pybind11/cast.h
vnpy_rohon/api/include/pybind11/chrono.h
vnpy_rohon/api/include/pybind11/common.h
vnpy_rohon/api/include/pybind11/complex.h
vnpy_rohon/api/include/pybind11/eigen.h
vnpy_rohon/api/include/pybind11/embed.h
vnpy_rohon/api/include/pybind11/eval.h
vnpy_rohon/api/include/pybind11/functional.h
vnpy_rohon/api/include/pybind11/iostream.h
