Metadata-Version: 2.1
Name: Ultron-Rohon
Version: 6.5.1.5.1
Summary: Rohon gateway for VeighNa quant trading framework.
Home-page: https://www.vnpy.com
Author: flagt
Author-email: flaght@gmail.com
License: MIT
Keywords: quant,quantitative,investment,trading,algotrading
Platform: UNKNOWN
Classifier: Development Status :: 5 - Production/Stable
Classifier: Operating System :: Microsoft :: Windows
Classifier: Operating System :: POSIX :: Linux
Classifier: Programming Language :: Python :: 3
Classifier: Programming Language :: Python :: 3.7
Classifier: Programming Language :: Python :: 3.8
Classifier: Programming Language :: Python :: 3.9
Classifier: Programming Language :: Python :: 3.10
Classifier: Topic :: Office/Business :: Financial :: Investment
Classifier: Programming Language :: Python :: Implementation :: CPython
Classifier: License :: OSI Approved :: MIT License
Classifier: Natural Language :: Chinese (Simplified)
